cubed_tube/__init__.py
cubed_tube/__main__.py
cubed_tube/main.py
cubed_tube/backend/__init__.py
cubed_tube/backend/cloud_storage.py
cubed_tube/backend/gunicorn_conf.py
cubed_tube/backend/memcached_client.py
cubed_tube/backend/server.py
cubed_tube/backend/user_state.py
cubed_tube/frontend/__init__.py
cubed_tube/frontend/render.py
cubed_tube/frontend/template_context.py
cubed_tube/frontend/templates/__init__.py
cubed_tube/frontend/templates/index.html
cubed_tube/frontend/templates/scripts/README.md
cubed_tube/frontend/templates/scripts/lib.js
cubed_tube/frontend/templates/scripts/main.js
cubed_tube/frontend/templates/scripts/modal_forms.js
cubed_tube/frontend/templates/scripts/user.js
cubed_tube/frontend/templates/scripts/videos.js
cubed_tube/frontend/templates/scripts/youtube.js
cubed_tube/frontend/templates/static/cod.png
cubed_tube/frontend/templates/static/favicon_disc128.png
cubed_tube/frontend/templates/static/favicon_disc16.png
cubed_tube/frontend/templates/static/favicon_disc196.png
cubed_tube/frontend/templates/static/favicon_disc32.png
cubed_tube/frontend/templates/static/favicon_disc64.png
cubed_tube/frontend/templates/static/manifest.webmanifest
cubed_tube/frontend/templates/static/style.css
cubed_tube/frontend/templates/static/triangle.svg
cubed_tube/lib/__init__.py
cubed_tube/lib/common.py
cubed_tube/lib/model_migration.py
cubed_tube/lib/models.py
cubed_tube/lib/schema.py
cubed_tube/lib/trends.py
cubed_tube/lib/util.py
cubed_tube/scraper/__init__.py
cubed_tube/scraper/scraper.py
cubed_tube/worker/__init__.py
cubed_tube/worker/worker.py
test/__init__.py
test/test_schema.py
test/test_trends.py
test/test_wsgi_user.py
cubedtube-0.1.20.dist-info/LICENSE
cubedtube-0.1.20.dist-info/METADATA
cubedtube-0.1.20.dist-info/WHEEL
cubedtube-0.1.20.dist-info/entry_points.txt
cubedtube-0.1.20.dist-info/top_level.txt
cubedtube-0.1.20.dist-info/RECORD
