Metadata-Version: 2.1
Name: cubedtube
Version: 0.1.20
Summary: A video viewing webapp that organizes videos into channels and series
Home-page: https://github.com/stevarino/cubed-tube
Author: stevarino
Author-email: stevarino@hermit.tube
License: UNKNOWN
Project-URL: Bug Tracker, https://github.com/stevarino/cubed-tube/issues
Platform: UNKNOWN
Requires-Python: >=3.6
License-File: LICENSE
Requires-Dist: Authlib (<=0.15.4)
Requires-Dist: awscli (>=1.19.97)
Requires-Dist: boto3 (>=1.17.97)
Requires-Dist: Flask (>=1.1.2)
Requires-Dist: gunicorn (>=20.0.0)
Requires-Dist: Jinja2 (>=3.0)
Requires-Dist: peewee (>=3.13.3)
Requires-Dist: prometheus-client (>=0.11.0)
Requires-Dist: pymemcache (>=3.5.0)
Requires-Dist: PyYAML (>=5.3.1)
Requires-Dist: requests (>=2.0)
